macrawlon/__init__.py
macrawlon/youtube_audio_and_video_downloader.py
macrawlon-0.1.dist-info/LICENSE
macrawlon-0.1.dist-info/METADATA
macrawlon-0.1.dist-info/WHEEL
macrawlon-0.1.dist-info/top_level.txt
macrawlon-0.1.dist-info/RECORD
