Metadata-Version: 2.1
Name: macrawlon
Version: 0.1
Summary: A sweet little collection of handy functions for video file downloading. 📼
Home-page: https://github.com/alexandrosstergiou/macrawlon
Author: Alexandros Stergiou
Author-email: alexstergiou5@gmail.com
License: MIT
License-File: LICENSE
Requires-Dist: pandas
Requires-Dist: youtube-dl
Requires-Dist: pafy
Requires-Dist: tqdm
